MANIFEST.in
README.md
setup.py
mixalime/__init__.py
mixalime/combine.py
mixalime/create.py
mixalime/diff.py
mixalime/export.py
mixalime/fit.py
mixalime/main.py
mixalime/plot.py
mixalime/tests.py
mixalime/utils.py
mixalime.egg-info/PKG-INFO
mixalime.egg-info/SOURCES.txt
mixalime.egg-info/dependency_links.txt
mixalime.egg-info/entry_points.txt
mixalime.egg-info/requires.txt
mixalime.egg-info/top_level.txt
mixalime/data/Lato-Medium.ttf
mixalime/data/Lato-Regular.ttf
mixalime/data/OFL.txt
mixalime/data/chip.tar.gz