Metadata-Version: 2.1
Name: mixalime
Version: 2.9.0
Summary: Identification of allele-specific events in sequencing experiments.
Home-page: https://github.com/autosome-ru/mixalime
Author: Georgy Meshcheryakov
Author-email: iam@georgy.top
Classifier: Programming Language :: Python :: 3.7
Classifier: Programming Language :: Python :: 3.8
Classifier: Programming Language :: Python :: 3.9
Classifier: Development Status :: 5 - Production/Stable
Classifier: Topic :: Scientific/Engineering
Classifier: Operating System :: OS Independent
Requires-Python: >=3.6, <3.10
